<?xml version="1.0" encoding="UTF-8"?>
<soapenv:Envelope xmlns:soapenv="http://www.w3.org/2003/05/soap-envelope">
   <soapenv:Header xmlns:wsa="http://www.w3.org/2005/08/addressing">
      <s:Security xmlns:s="http://docs.oasis-open.org/wss/2004/01/oasis-200401-wss-wssecurity-secext-1.0.xsd" xmlns:u="http://docs.oasis-open.org/wss/2004/01/oasis-200401-wss-wssecurity-utility-1.0.xsd">
         <u:Timestamp>
            <u:Created>2016-02-03T06:36:22.64Z</u:Created>
         </u:Timestamp>
      </s:Security>
      <v100:LookupKey xmlns:v100="http://eaf4esb.wesb.uhc.com/schema/framework/EAF4ESBLookupKey/v1_00">
         <v100:environment>test_sys1</v100:environment>
      </v100:LookupKey>
      <wsa:Action>http://eaf4esb.wesb.uhc.com/schema/contract/planpolicy/getlistpolicy/v1_10/GetListPolicy/getListPolicyInfoResponse</wsa:Action>
      <wsa:RelatesTo>urn:uuid:347fb6d8-b359-4f16-9f59-c2a3ece6af85</wsa:RelatesTo>
   </soapenv:Header>
   <soapenv:Body>
      <v110:getListPolicyInfoResponse xmlns:v110="http://eaf4esb.wesb.uhc.com/schema/contract/planpolicy/getlistpolicy/v1_10" xmlns:v210="http://ovations.unitedhealthgroup.com/schema/ovations/planpolicy/regionplan/v2_10" xmlns:v210_1="http://ovations.unitedhealthgroup.com/schema/ovations/planpolicy/individual/v2_10" xmlns:v210_2="http://ovations.unitedhealthgroup.com/schema/ovations/common/v2_10" xmlns:v210_3="http://ovations.unitedhealthgroup.com/schema/ovations/planpolicy/plan/v2_10" xmlns:v210_4="http://ovations.unitedhealthgroup.com/schema/ovations/provider/ovaprovider/v2_10" xmlns:v210_5="http://ovations.unitedhealthgroup.com/schema/ovations/consumer/v2_10" xmlns:v400="http://enterprise.unitedhealthgroup.com/schema/canoncial/base/common/v4_00" xmlns:v400_1="http://enterprise.unitedhealthgroup.com/schema/canoncial/provider/provider/v4_00" xmlns:v403="http://enterprise.unitedhealthgroup.com/schema/canoncial/planpolicy/plan/v4_03">
         <v110:GetListPolicyResponse>
            <ConsumerAccount BusinessType="GOVT">
               <Individual>
                  <Plan>
                     <v403:PlanID>46483530</v403:PlanID>
                     <v403:Contract>
                        <v403:ContractNo>H0755</v403:ContractNo>
                     </v403:Contract>
                     <v403:PBPNo>030</v403:PBPNo>
                     <v403:BusinessSegment>SECUREHORIZONS</v403:BusinessSegment>
                     <v403:PlanTypeCode>HMO</v403:PlanTypeCode>
                     <v403:PlanName>UnitedHealthcare MedicareComplete Plan 1 (HMO)</v403:PlanName>
                     <v403:EffectiveDates>
                        <v400:StartDate>2016-01-01</v400:StartDate>
                     </v403:EffectiveDates>
                     <v210:RegionID>1447</v210:RegionID>
                     <v210:RxPlanInd>Y</v210:RxPlanInd>
                     <v210_1:AdditionalAttribute>
                        <v210_2:Name>ElectionType</v210_2:Name>
                        <v210_2:Value>SPECIAL (SEP)</v210_2:Value>
                     </v210_1:AdditionalAttribute>
                     <v210_1:AdditionalAttribute>
                        <v210_2:Name>PlanMemberNo</v210_2:Name>
                        <v210_2:Value>839423163-1</v210_2:Value>
                     </v210_1:AdditionalAttribute>
                     <v210_1:AdditionalAttribute>
                        <v210_2:Name>PlanSystemTypeID</v210_2:Name>
                        <v210_2:Value>COSMOS</v210_2:Value>
                     </v210_1:AdditionalAttribute>
                     <v210_1:PlanProfile>
                        <v210_3:EffectiveDates>
                           <v400:StartDate>2016-01-01</v400:StartDate>
                           <v400:StopDate>9999-12-31</v400:StopDate>
                        </v210_3:EffectiveDates>
                        <v210_3:UncoveredMonths>0</v210_3:UncoveredMonths>
                        <v210_3:CredibleCoverageInd>Y</v210_3:CredibleCoverageInd>
                        <v210_3:NetLepAmount>0</v210_3:NetLepAmount>
                        <v210_3:CopayCategoryID>0</v210_3:CopayCategoryID>
                     </v210_1:PlanProfile>
                     <v210_1:PlanGroup>
                        <v403:GroupNo>27040</v403:GroupNo>
                        <v403:MasterGroupNo>200119</v403:MasterGroupNo>
                        <v403:SourceSystemID>
                           <v400:Name>Site</v400:Name>
                           <v400:Value>NYC</v400:Value>
                        </v403:SourceSystemID>
                        <v403:EffectiveDates>
                           <v400:StartDate>2016-01-01</v400:StartDate>
                           <v400:StopDate>9999-12-31</v400:StopDate>
                        </v403:EffectiveDates>
                     </v210_1:PlanGroup>
                     <v210_1:Provider>
                        <v210_4:ProviderIdentity>
                           <v400_1:MPIN>00040025527</v400_1:MPIN>
                        </v210_4:ProviderIdentity>
                        <v210_4:EffectiveDates>
                           <v400:StartDate>2016-01-01</v400:StartDate>
                           <v400:StopDate>9999-12-31</v400:StopDate>
                        </v210_4:EffectiveDates>
                        <v210_4:Name>SCHWARTZ, D.O., MICHAEL B.</v210_4:Name>
                        <v210_4:OverrideInd>true</v210_4:OverrideInd>
                     </v210_1:Provider>
                     <v210_1:PlanCode>UH1</v210_1:PlanCode>
                     <v210_1:PlanCategory>MAPD</v210_1:PlanCategory>
                     <v210_1:PlanStatus>ACTIVE</v210_1:PlanStatus>
                     <v210_1:RxInfo>
                        <v210_3:RxBin>610097</v210_3:RxBin>
                        <v210_3:RxGroup>COS</v210_3:RxGroup>
                        <v210_3:RxPCN>9999</v210_3:RxPCN>
                     </v210_1:RxInfo>
                  </Plan>
                  <Plan>
                     <v403:PlanID>41444039</v403:PlanID>
                     <v403:Contract>
                        <v403:ContractNo>H0755</v403:ContractNo>
                     </v403:Contract>
                     <v403:PBPNo>030</v403:PBPNo>
                     <v403:BusinessSegment>SECUREHORIZONS</v403:BusinessSegment>
                     <v403:PlanTypeCode>HMO</v403:PlanTypeCode>
                     <v403:PlanName>UnitedHealthcare MedicareComplete Plan 1 (HMO)</v403:PlanName>
                     <v403:EffectiveDates>
                        <v400:StartDate>2015-01-01</v400:StartDate>
                        <v400:StopDate>2015-12-31</v400:StopDate>
                     </v403:EffectiveDates>
                     <v210:RegionID>1447</v210:RegionID>
                     <v210:RxPlanInd>Y</v210:RxPlanInd>
                     <v210_1:AdditionalAttribute>
                        <v210_2:Name>ElectionType</v210_2:Name>
                        <v210_2:Value>SEP ADMINISTRATIVE ACTION</v210_2:Value>
                     </v210_1:AdditionalAttribute>
                     <v210_1:AdditionalAttribute>
                        <v210_2:Name>PlanMemberNo</v210_2:Name>
                        <v210_2:Value>839423163-1</v210_2:Value>
                     </v210_1:AdditionalAttribute>
                     <v210_1:AdditionalAttribute>
                        <v210_2:Name>PlanSystemTypeID</v210_2:Name>
                        <v210_2:Value>COSMOS</v210_2:Value>
                     </v210_1:AdditionalAttribute>
                     <v210_1:PlanProfile>
                        <v210_3:EffectiveDates>
                           <v400:StartDate>2015-01-01</v400:StartDate>
                           <v400:StopDate>9999-12-31</v400:StopDate>
                        </v210_3:EffectiveDates>
                        <v210_3:UncoveredMonths>0</v210_3:UncoveredMonths>
                        <v210_3:CredibleCoverageInd>Y</v210_3:CredibleCoverageInd>
                        <v210_3:NetLepAmount>0</v210_3:NetLepAmount>
                        <v210_3:CopayCategoryID>0</v210_3:CopayCategoryID>
                     </v210_1:PlanProfile>
                     <v210_1:PlanGroup>
                        <v403:GroupNo>27040</v403:GroupNo>
                        <v403:MasterGroupNo>200119</v403:MasterGroupNo>
                        <v403:SourceSystemID>
                           <v400:Name>Site</v400:Name>
                           <v400:Value>NYC</v400:Value>
                        </v403:SourceSystemID>
                        <v403:EffectiveDates>
                           <v400:StartDate>2015-01-01</v400:StartDate>
                           <v400:StopDate>2015-12-31</v400:StopDate>
                        </v403:EffectiveDates>
                     </v210_1:PlanGroup>
                     <v210_1:Provider>
                        <v210_4:ProviderIdentity>
                           <v400_1:MPIN>00040025527</v400_1:MPIN>
                        </v210_4:ProviderIdentity>
                        <v210_4:EffectiveDates>
                           <v400:StartDate>2015-01-01</v400:StartDate>
                           <v400:StopDate>9999-12-31</v400:StopDate>
                        </v210_4:EffectiveDates>
                        <v210_4:Name>SCHWARTZ, D.O., MICHAEL B.</v210_4:Name>
                        <v210_4:OverrideInd>true</v210_4:OverrideInd>
                     </v210_1:Provider>
                     <v210_1:PlanCode>UH1</v210_1:PlanCode>
                     <v210_1:PlanCategory>MAPD</v210_1:PlanCategory>
                     <v210_1:PlanStatus>TERMINATED</v210_1:PlanStatus>
                     <v210_1:RxInfo>
                        <v210_3:RxBin>610097</v210_3:RxBin>
                        <v210_3:RxGroup>COS</v210_3:RxGroup>
                        <v210_3:RxPCN>9999</v210_3:RxPCN>
                     </v210_1:RxInfo>
                  </Plan>
                  <Plan>
                     <v403:PlanID>24525479</v403:PlanID>
                     <v403:Contract>
                        <v403:ContractNo>H0755</v403:ContractNo>
                     </v403:Contract>
                     <v403:PBPNo>030</v403:PBPNo>
                     <v403:BusinessSegment>SECUREHORIZONS</v403:BusinessSegment>
                     <v403:PlanTypeCode>HMO</v403:PlanTypeCode>
                     <v403:PlanName>UnitedHealthcare MedicareComplete Plan 1 (HMO)</v403:PlanName>
                     <v403:EffectiveDates>
                        <v400:StartDate>2011-01-01</v400:StartDate>
                        <v400:StopDate>2014-12-31</v400:StopDate>
                     </v403:EffectiveDates>
                     <v210:RegionID>1447</v210:RegionID>
                     <v210:RxPlanInd>Y</v210:RxPlanInd>
                     <v210_1:AdditionalAttribute>
                        <v210_2:Name>ElectionType</v210_2:Name>
                        <v210_2:Value>SEP ADMINISTRATIVE ACTION</v210_2:Value>
                     </v210_1:AdditionalAttribute>
                     <v210_1:AdditionalAttribute>
                        <v210_2:Name>PlanMemberNo</v210_2:Name>
                        <v210_2:Value>839423163-1</v210_2:Value>
                     </v210_1:AdditionalAttribute>
                     <v210_1:AdditionalAttribute>
                        <v210_2:Name>PlanSystemTypeID</v210_2:Name>
                        <v210_2:Value>COSMOS</v210_2:Value>
                     </v210_1:AdditionalAttribute>
                     <v210_1:PlanProfile>
                        <v210_3:EffectiveDates>
                           <v400:StartDate>2011-01-01</v400:StartDate>
                           <v400:StopDate>9999-12-31</v400:StopDate>
                        </v210_3:EffectiveDates>
                        <v210_3:UncoveredMonths>0</v210_3:UncoveredMonths>
                        <v210_3:CredibleCoverageInd>Y</v210_3:CredibleCoverageInd>
                        <v210_3:CopayCategoryID>0</v210_3:CopayCategoryID>
                     </v210_1:PlanProfile>
                     <v210_1:PlanGroup>
                        <v403:GroupNo>27040</v403:GroupNo>
                        <v403:MasterGroupNo>200119</v403:MasterGroupNo>
                        <v403:SourceSystemID>
                           <v400:Name>Site</v400:Name>
                           <v400:Value>NYC</v400:Value>
                        </v403:SourceSystemID>
                        <v403:EffectiveDates>
                           <v400:StartDate>2011-01-01</v400:StartDate>
                           <v400:StopDate>2014-12-31</v400:StopDate>
                        </v403:EffectiveDates>
                     </v210_1:PlanGroup>
                     <v210_1:Provider>
                        <v210_4:ProviderIdentity>
                           <v400_1:MPIN>00000099000</v400_1:MPIN>
                        </v210_4:ProviderIdentity>
                        <v210_4:EffectiveDates>
                           <v400:StartDate>2011-07-01</v400:StartDate>
                           <v400:StopDate>2012-05-31</v400:StopDate>
                        </v210_4:EffectiveDates>
                        <v210_4:Name>PCP Not Selected</v210_4:Name>
                        <v210_4:OverrideInd>true</v210_4:OverrideInd>
                     </v210_1:Provider>
                     <v210_1:Provider>
                        <v210_4:ProviderIdentity>
                           <v400_1:MPIN>00040025527</v400_1:MPIN>
                        </v210_4:ProviderIdentity>
                        <v210_4:EffectiveDates>
                           <v400:StartDate>2012-06-01</v400:StartDate>
                           <v400:StopDate>9999-12-31</v400:StopDate>
                        </v210_4:EffectiveDates>
                        <v210_4:Name>SCHWARTZ, D.O., MICHAEL B.</v210_4:Name>
                        <v210_4:OverrideInd>true</v210_4:OverrideInd>
                     </v210_1:Provider>
                     <v210_1:Provider>
                        <v210_4:ProviderIdentity>
                           <v400_1:MPIN>00040025528</v400_1:MPIN>
                        </v210_4:ProviderIdentity>
                        <v210_4:EffectiveDates>
                           <v400:StartDate>2011-01-01</v400:StartDate>
                           <v400:StopDate>2011-06-30</v400:StopDate>
                        </v210_4:EffectiveDates>
                        <v210_4:Name>SCHWARTZ, D.O., MICHAEL B.</v210_4:Name>
                        <v210_4:OverrideInd>false</v210_4:OverrideInd>
                     </v210_1:Provider>
                     <v210_1:PlanCode>UH1</v210_1:PlanCode>
                     <v210_1:PlanCategory>MAPD</v210_1:PlanCategory>
                     <v210_1:PlanStatus>TERMINATED</v210_1:PlanStatus>
                     <v210_1:RxInfo>
                        <v210_3:RxBin>610097</v210_3:RxBin>
                        <v210_3:RxGroup>COS</v210_3:RxGroup>
                        <v210_3:RxPCN>9999</v210_3:RxPCN>
                     </v210_1:RxInfo>
                  </Plan>
                  <Consumer>
                     <v210_5:OvationsMemberProfile>
                        <v210_5:MemberNo>839423163-1</v210_5:MemberNo>
                        <v210_5:SystemID>
                           <v210_5:MemberNoSystemID>COSMOS</v210_5:MemberNoSystemID>
                        </v210_5:SystemID>
                        <v210_5:EffectiveDates>
                           <v400:StartDate>2010-11-01</v400:StartDate>
                        </v210_5:EffectiveDates>
                     </v210_5:OvationsMemberProfile>
                  </Consumer>
               </Individual>
            </ConsumerAccount>
         </v110:GetListPolicyResponse>
      </v110:getListPolicyInfoResponse>
   </soapenv:Body>
</soapenv:Envelope>
