{
"url":null,
"expectedData":{
"footerHomeLink":{
"identifier":"id",
"elementName":"gf_lnk_1"
},
"footerAboutUsLink":{
"identifier":"id",
"elementName":"gf_lnk_2"
},
"footerContactUsLink":{
"identifier":"id",
"elementName":"gf_lnk_3"
},
"footerSiteMapLink":{
"identifier":"id",
"elementName":"gf_lnk_4"
},
"footerPrivacyPolicyLink":{
"identifier":"id",
"elementName":"gf_lnk_5"
},
"footerTermsofUseLink":{
"identifier":"id",
"elementName":"gf_lnk_6"
},
"footerDisclaimersLink":{
"identifier":"id",
"elementName":"gf_lnk_7"
},
"footerAgentsnBrokersLink":{
"identifier":"id",
"elementName":"gf_lnk_8"
}
}
}