{
"url":null,
"expectedData":{
"planName":{
"identifier":"xpath",
"elementName":"//div[@class='plan__header']/h2"
},
"planStatus":{
"identifier":"className",
"elementName":"plan__status"
},
"memberDetails":{
"identifier":"className",
"elementName":"detail"
},
"viewIdCardLink":{
"identifier":"linkText",
"elementName":" View ID Card"
},
"medicalBenefits":{
"identifier":"xpath",
"elementName":"//div[@class='tile tile--benefits-overview tablet-2col clear-left']/descendant::ul[@class='benefit-list']"
},
"medicalBenefitsDetailsLink":{
"identifier":"xpath",
"elementName":"//div[@class='tile tile--benefits-overview tablet-2col clear-left']/a"
},
"drugBenefits":{
"identifier":"xpath",
"elementName":"//ul[@class='benefit-list narrow-value']/descendant::li[@class='leader ng-scope']"
},
"drugBenefitsDetailsLink":{
"identifier":"xpath",
"elementName":"//div[@class='tile tile--benefits-overview tablet-2col']/a"
}
}
}