	{
"url":null,
"expectedData":{
"myCareMessages":{
"identifier":"xpath",
"elementName":"//div[@id='phr_widget_1_box']"
},
"drugInformation":{
"identifier":"xpath",
"elementName":"//div[@id='phr_widget_2_box']"
},
"myFacilitiesInformation":{
"identifier":"xpath",
"elementName":"//div[@id='phr_widget_3_box']"
},
"planName1":{
"identifier":"xpath",
"elementName":"//div[@id='phr_widget_4_box']/div[2]/h3/strong"
},
"memberId1":{
"identifier":"xpath",
"elementName":"//table[@class='my_prod_table']/tbody/tr[2]/td[2]/p"
},
"myProductInformation":{
"identifier":"xpath",
"elementName":"//div[@id='phr_widget_4_box']"
},
"myDoctorInformation":{
"identifier":"xpath",
"elementName":"//div[@id='phr_widget_5_box']"
},
"myHealthConcerns":{
"identifier":"xpath",
"elementName":"//div[@id='phr_widget_6_box']"
},
"pharmacyInformation":{
"identifier":"xpath",
"elementName":"//div[@id='phr_widget_7_box']"
},
"quizzesAndAssessments":{
"identifier":"id",
"elementName":"phr_widget_8_box"
},
"memberName":{
"identifier":"id",
"elementName":"welcomeText"
},
"planStatus1":{
"identifier":"id",
"elementName":"status"
},
"primaryCareProvider":
{
"identifier":"xpath",
"elementName":"//div[@id='planinformation']/div[2]/div[7]/span[2]"
}
}
}