{  
   "url":null,
   "expectedData":{  
      "memberId1":{  
         "identifier":"xpath",
         "elementName":"//div[@id='pdpPageNonLis']/div[1]/div/div[1]/div/div[2]/div/table/tbody/tr[1]/td[2]"
      },
      "effectiveDate":{  
         "identifier":"xpath",
         "elementName":"//div[@id='pdpPageNonLis']/div[1]/div/div[1]/div/div[2]/div/table/tbody/tr[2]/td[2]"
      },
      "monthlyPremium":{  
         "identifier":"xpath",
         "elementName":"//div[@id='pdpPageNonLis']/div[1]/div/div[1]/div/div[2]/div/table/tbody/tr[3]/td[2]"
      },
      "initialCoverageTier1":{  
         "identifier":"xpath",
         "elementName":"//div[@id='pdpPageNonLis']/div[1]/div/div[2]/div[1]/div[1]/div[1]/div/div[1]/div[2]/div[3]/div[1]/div[1]/div[2]/div[1]/table/tbody/tr[1]/td[3]"
      },
      "initialCoverageTier2":{  
         "identifier":"xpath",
         "elementName":"//div[@id='pdpPageNonLis']/div[1]/div/div[2]/div[1]/div[1]/div[1]/div/div[1]/div[2]/div[3]/div[1]/div[1]/div[2]/div[1]/table/tbody/tr[2]/td[3]"
      },
      "initialCoverageTier3":{  
         "identifier":"xpath",
         "elementName":"//div[@id='pdpPageNonLis']/div[1]/div/div[2]/div[1]/div[1]/div[1]/div/div[1]/div[2]/div[3]/div[1]/div[1]/div[2]/div[1]/table/tbody/tr[3]/td[3]"
      },
      "initialCoverageTier4":{  
         "identifier":"xpath",
         "elementName":"//div[@id='pdpPageNonLis']/div[1]/div/div[2]/div[1]/div[1]/div[1]/div/div[1]/div[2]/div[3]/div[1]/div[1]/div[2]/div[1]/table/tbody/tr[4]/td[3]"
      },
      "initialCoverageTier5":{  
         "identifier":"xpath",
         "elementName":"//div[@id='pdpPageNonLis']/div[1]/div/div[2]/div[1]/div[1]/div[1]/div/div[1]/div[2]/div[3]/div[1]/div[1]/div[2]/div[1]/table/tbody/tr[5]/td[3]"
      },
      "drugCopayDiscountsLink":{  
         "identifier":"xpath",
         "elementName":"//div[@id='pdpPageNonLis']/div[1]/div/div[2]/div[1]/div[1]/div[1]/div/div[1]/div[2]/div[3]/div[1]/div[1]/div[2]/div[1]/p[2]/a"
      },
      "prescriptionDrugCostBenefitsLink":{  
         "identifier":"xpath",
         "elementName":"//div[@id='pdpPageNonLis']/div[1]/div/div[2]/div[1]/div[1]/div[1]/div/div[1]/div[2]/div[3]/div[1]/div[1]/div[2]/div[1]/p[3]/a[2]"
      },
      "drugLookupLink":{  
         "identifier":"xpath",
         "elementName":"//div[@id='pdpPageNonLis']/div[1]/div/div[2]/div[1]/div[1]/div[1]/div/div[1]/div[2]/div[3]/div[1]/div[2]/div[2]/div[1]/p[1]/a"
      },
      "preferredRetailPharmacyLink":{  
         "identifier":"xpath",
         "elementName":"//div[@id='grayBox_a58997fc-9292-4f99-8c04-1d56426f5ba7']/div[1]/div[1]/div[1]/div[2]/div[1]/a"
      },
      "preferredRetailPharmacyCopayLink":{  
         "identifier":"xpath",
         "elementName":"//div[@id='grayBox_a58997fc-9292-4f99-8c04-1d56426f5ba7']/div[1]/div[1]/div[1]/div[2]/div[1]/p/a"
      },
      "preferredMailPharmacyCopayLink":{  
         "identifier":"xpath",
         "elementName":"//div[@id='grayBox_a58997fc-9292-4f99-8c04-1d56426f5ba7']/div[1]/div[1]/div[1]/div[6]/div[1]/p[2]/a[2]"
      },
      "lowerTierDrugSection":{  
         "identifier":"xpath",
         "elementName":"//div[@id='grayBox_a58997fc-9292-4f99-8c04-1d56426f5ba7']/div[1]/div[2]"
      },
      "drugCostTablePrescriptionDrugCostBenefits":{  
         "identifier":"xpath",
         "elementName":"//div[@id='pdpPageNonLis']/div[1]/div/div[3]"
      },
      "prpdc_tier1":{  
         "identifier":"xpath",
         "elementName":"//div[@id='preferredRetail']/div[1]/div[1]/div[2]/table/tbody/tr[2]"
      },
      "prpdc_tier2":{  
         "identifier":"xpath",
         "elementName":"//div[@id='preferredRetail']/div[1]/div[1]/div[2]/table/tbody/tr[3]"
      },
      "prpdc_tier3":{  
         "identifier":"xpath",
         "elementName":"//div[@id='preferredRetail']/div[1]/div[1]/div[2]/table/tbody/tr[4]"
      },
      "prpdc_tier4":{  
         "identifier":"xpath",
         "elementName":"//div[@id='preferredRetail']/div[1]/div[1]/div[2]/table/tbody/tr[5]"
      },
      "prpdc_tier5":{  
         "identifier":"xpath",
         "elementName":"//div[@id='preferredRetail']/div[1]/div[1]/div[2]/table/tbody/tr[6]"
      },
      "snprdc_tier1":{  
         "identifier":"xpath",
         "elementName":"//div[@id='StandardNetworkPharmacyRetail']/div[1]/div[1]/div[2]/table/tbody/tr[2]"
      },
      "snprdc_tier2":{  
         "identifier":"xpath",
         "elementName":"//div[@id='StandardNetworkPharmacyRetail']/div[1]/div[1]/div[2]/table/tbody/tr[3]"
      },
      "snprdc_tier3":{  
         "identifier":"xpath",
         "elementName":"//div[@id='StandardNetworkPharmacyRetail']/div[1]/div[1]/div[2]/table/tbody/tr[4]"
      },
      "snprdc_tier4":{  
         "identifier":"xpath",
         "elementName":"//div[@id='StandardNetworkPharmacyRetail']/div[1]/div[1]/div[2]/table/tbody/tr[5]"
      },
      "snprdc_tier5":{  
         "identifier":"xpath",
         "elementName":"//div[@id='StandardNetworkPharmacyRetail']/div[1]/div[1]/div[2]/table/tbody/tr[6]"
      },
      "pmspdc_tier1":{  
         "identifier":"xpath",
         "elementName":"//div[@class='pdpNonLisPageIncludes_4 MailOrder_PreferredMailService parbase']/div[1]/div[2]/table/tbody/tr[2]"
      },
      "pmspdc_tier2":{  
         "identifier":"xpath",
         "elementName":"//div[@class='pdpNonLisPageIncludes_4 MailOrder_PreferredMailService parbase']/div[1]/div[2]/table/tbody/tr[3]"
      },
      "pmspdc_tier3":{  
         "identifier":"xpath",
         "elementName":"//div[@class='pdpNonLisPageIncludes_4 MailOrder_PreferredMailService parbase']/div[1]/div[2]/table/tbody/tr[4]"
      },
      "pmspdc_tier4":{  
         "identifier":"xpath",
         "elementName":"//div[@class='pdpNonLisPageIncludes_4 MailOrder_PreferredMailService parbase']/div[1]/div[2]/table/tbody/tr[5]"
      },
      "pmspdc_tier5":{  
         "identifier":"xpath",
         "elementName":"//div[@class='pdpNonLisPageIncludes_4 MailOrder_PreferredMailService parbase']/div[1]/div[2]/table/tbody/tr[6]"
      },
      "planBenefitsHighlights":{  
         "identifier":"xpath",
         "elementName":"//div[@class='pdpNonLisPageIncludes_5 parsys']/div[1]/div[1]/div[2]/div[2]/div/div/div[1]/div[1]/div/div/div[1]/div[2]/div[1]"
      },
      "formsAndResourcses":{  
         "identifier":"xpath",
         "elementName":"//div[@class='pdpNonLisPageIncludes_5 parsys']/div[1]/div[1]/div[2]/div[2]/div/div/div[1]/div[2]/div/div/div[1]/div[2]/div[2]/div[1]"
      },
      "tfnInformation":{  
         "identifier":"xpath",
         "elementName":"//div[@class='pdpNonLisPageIncludes_5 parsys']/div[1]/div[1]/div[2]/div[2]/div/div/div[1]/div[3]/div/div/div[1]/div[2]"
      },
      "footNotes":{  
         "identifier":"xpath",
         "elementName":"//div[@class='pdpNonLisPageIncludes_5 parsys']/div[2]/div[1]/div[2]/div[1]"
      },
      "rr_druglookupwidget":{  
         "identifier":"id",
         "elementName":"_content_campaigns_aarpm_plan-benefits-right-main_right-rail_jcr_content_par_teaser_0"
      },
      "planStatus1":{  
         "identifier":"id",
         "elementName":"status"
      },
      "planName1":{  
         "identifier":"xpath",
         "elementName":"//div[@id='planinformation']/div[2]/h3/a"
      },
      "memberName":{  
         "identifier":"id",
         "elementName":"welcomeText"
      },
      "primaryCareProviderTier1":{  
         "identifier":"xpath",
         "elementName":"//div[@id='grayBox_2ca1fdae-8fc8-4597-b277-e2350c43be93/downParsys/benefitscontainer_6b/mapdLisPageIncludes/columncontrol_ef3c/topcontainer1/outerbox_3953']/div[1]/div[1]/div[2]/div[1]/table[1]/tbody/tr[2]"
      },
      "primaryCareProviderTier2":{  
         "identifier":"xpath",
         "elementName":"//div[@id='grayBox_2ca1fdae-8fc8-4597-b277-e2350c43be93/downParsys/benefitscontainer_6b/mapdLisPageIncludes/columncontrol_ef3c/topcontainer1/outerbox_3953']/div[1]/div[1]/div[2]/div[1]/table[1]/tbody/tr[3]"
      },
      "specialistTier1":{  
         "identifier":"xpath",
         "elementName":"//div[@id='grayBox_2ca1fdae-8fc8-4597-b277-e2350c43be93/downParsys/benefitscontainer_6b/mapdLisPageIncludes/columncontrol_ef3c/topcontainer1/outerbox_3953']/div[1]/div[1]/div[2]/div[1]/table[2]/tbody/tr[5]/td/label"
      },
      "specialistTier1":{  
         "identifier":"xpath",
         "elementName":"//div[@id='grayBox_2ca1fdae-8fc8-4597-b277-e2350c43be93/downParsys/benefitscontainer_6b/mapdLisPageIncludes/columncontrol_ef3c/topcontainer1/outerbox_3953']/div[1]/div[1]/div[2]/div[1]/table[3]/tbody/tr/td"
      }
   }
}