{
"url":null,
"expectedData":{
"myCareMessages":{
"identifier":"xpath",
"elementName":"//div[@id='phr_widget_1_box']/div[3]/p"
},
"drugInformation":{
"identifier":"xpath",
"elementName":"//div[@id='phr_widget_2_box']/div[3]/p"
},
"savedDrugName":{
"identifier":"xpath",
"elementName":"//div[@id='phr_widget_2_box']/div[6]/div[1]"
},
"estimateCostLink":{
"identifier":"xpath",
"elementName":"//div[@id='phr_widget_2_box']/div[6]/p/a"
},
"additionalInformationLink":{
"identifier":"xpath",
"elementName":"//div[@id='phr_widget_2_box']/div[9]/p/a"
},
"myFacilitiesInformation":{
"identifier":"xpath",
"elementName":"//div[@id='phr_widget_3_box']/div[3]/p"
},
"addFaclitiesLink":{
"identifier":"xpath",
"elementName":"//div[@id='phr_widget_3_box']/div[6]/p/a"
},
"planName1":{
"identifier":"xpath",
"elementName":"//div[@id='phr_widget_4_box']/div[2]/h3/strong"
},
"effectiveDate":{
"identifier":"xpath",
"elementName":"//table[@class='my_prod_table']/tbody/tr[1]/td[2]/p"
},
"memberId1":{
"identifier":"xpath",
"elementName":"//table[@class='my_prod_table']/tbody/tr[2]/td[2]/p"
},
"myProductsPlanBenefitsLink":{
"identifier":"xpath",
"elementName":"//div[@id='phr_widget_4_box']/div[2]/p[2]/a"
},
"myDoctorInformation":{
"identifier":"xpath",
"elementName":"//div[@id='phr_widget_5_box']/div[3]/p"
},
"myHealthConcerns":{
"identifier":"xpath",
"elementName":"//div[@id='phr_widget_6_box']/div[2]/p"
},
"pharmacyInformation":{
"identifier":"xpath",
"elementName":"//div[@id='phr_widget_7_box']/div[3]/p"
},
"addPharmacyLink":{
"identifier":"xpath",
"elementName":"//div[@id='phr_widget_7_box']/div[6]/p/a"
},
"preferredMailServicePharmacyLink":{
"identifier":"xpath",
"elementName":"//div[@id='phr_widget_7_box']/div[9]/p[1]/a"
},
"pharmacyLocatorLink":{
"identifier":"xpath",
"elementName":"//div[@id='phr_widget_7_box']/div[12]/p[2]/a"
},
"quizzesAndAssessments":{
"identifier":"id",
"elementName":"phr_widget_8_box"
},
"memberName":{
"identifier":"id",
"elementName":"welcomeText"
},
"planStatus1":{
"identifier":"xpath",
"elementName":"//div[@id='planinformation']/div[2]/div[5]/span[2]"
},
"groupId1":
{
"identifier":"xpath",
"elementName":"//div[@id='planinformation']/div[2]/div[1]/span[2]"
}
}
}