{"summaryHeading":"2017 Medicare Advantage Plans","planNames":[{"vppplanheading":"Compare\nAARP MedicareComplete SecureHorizons Plan 1 (HMO)    "},{"vppplanheading":"Compare\nAARP MedicareComplete SecureHorizons Essential (HMO)    "},{"vppplanheading":"Compare\nAARP MedicareComplete SecureHorizons Plan 2 (HMO)    "},{"vppplanheading":"Compare\nAARP MedicareComplete SecureHorizons Plan 3 (HMO)    "}],"planhighlights":"Highlights\n$0 premium.\nCovers care you receive through our network of local doctors and hospitals.\nMay require referral."}